{
  "violation_rate": 0.08,
  "collision_rate": 0.0,
  "near_miss_rate": 0.36,
  "intervention_rate": 0.8133333333333334,
  "override_success_rate": 0.9016393442622951,
  "mean_intervention_delay": 0.0,
  "operator_workload": 0.8133333333333334,
  "mean_drift": 12.396518889734677,
  "p95_drift": 28.899188353774914,
  "mean_latency_ms": 0.6040222616866231,
  "risk_mean": 0.8385874795041411,
  "risk_p05": 0.24599999999988328,
  "risk_p25": 1.0,
  "risk_p50": 1.0,
  "risk_p75": 1.0,
  "risk_p95": 1.0,
  "separation_risk_mean": 0.2074914631312566,
  "congestion_risk_mean": 0.1803920371040678,
  "speed_risk_mean": 0.9767563944007325,
  "uncertainty_risk_mean": 0.6379323874773102,
  "human_activation_count": 122,
  "cooldown_skips": 28,
  "suppressed_request_count": 28,
  "suppressed_critical_count": 0,
  "cooldown_release_count": 117,
  "critical_override_count": 117,
  "critical_trigger_rate": 0.78,
  "trigger_active_rate": 1.0,
  "confidence_mean": 0.9500000000000002,
  "false_intervention_rate": 0.08196721311475409,
  "repeated_intervention_rate": 0.9426229508196722,
  "post_intervention_violation_rate": 0.09022556390977443,
  "mean_drift_after_intervention": 13.718675147066884,
  "min_predicted_distance_mean": 5.005191276577316
}