{
  "violation_rate": 0.08,
  "collision_rate": 0.0,
  "near_miss_rate": 0.04666666666666667,
  "intervention_rate": 0.76,
  "override_success_rate": 0.8947368421052632,
  "mean_intervention_delay": 0.0,
  "operator_workload": 0.76,
  "mean_drift": 15.767844016140463,
  "p95_drift": 35.24676551449326,
  "mean_latency_ms": 0.43588577924917143,
  "risk_mean": 0.8011394157140949,
  "risk_p05": 0.2459999999999096,
  "risk_p25": 0.5251990229872783,
  "risk_p50": 1.0,
  "risk_p75": 1.0,
  "risk_p95": 1.0,
  "separation_risk_mean": 0.03756311958639374,
  "congestion_risk_mean": 0.035327910651426084,
  "speed_risk_mean": 0.9842165091325643,
  "uncertainty_risk_mean": 0.6384988009061447,
  "human_activation_count": 114,
  "cooldown_skips": 36,
  "suppressed_request_count": 36,
  "suppressed_critical_count": 0,
  "cooldown_release_count": 106,
  "critical_override_count": 106,
  "critical_trigger_rate": 0.7066666666666667,
  "trigger_active_rate": 1.0,
  "confidence_mean": 0.9000000000000004,
  "false_intervention_rate": 0.07894736842105263,
  "repeated_intervention_rate": 0.9210526315789473,
  "post_intervention_violation_rate": 0.0859375,
  "mean_drift_after_intervention": 18.626424620105677,
  "min_predicted_distance_mean": 12.282019674741209
}