{
  "violation_rate": 0.03333333333333333,
  "collision_rate": 0.0,
  "near_miss_rate": 0.5266666666666666,
  "intervention_rate": 0.8333333333333334,
  "override_success_rate": 0.96,
  "mean_intervention_delay": 0.0,
  "operator_workload": 0.8333333333333334,
  "mean_drift": 7.591423434168435,
  "p95_drift": 22.182301210371882,
  "mean_latency_ms": 0.46524303033947945,
  "risk_mean": 0.8811943678575839,
  "risk_p05": 0.3520848133163759,
  "risk_p25": 1.0,
  "risk_p50": 1.0,
  "risk_p75": 1.0,
  "risk_p95": 1.0,
  "separation_risk_mean": 0.3858488246503293,
  "congestion_risk_mean": 0.23601195534608427,
  "speed_risk_mean": 0.8448786686594966,
  "uncertainty_risk_mean": 0.6292022892537777,
  "human_activation_count": 125,
  "cooldown_skips": 25,
  "suppressed_request_count": 25,
  "suppressed_critical_count": 0,
  "cooldown_release_count": 114,
  "critical_override_count": 114,
  "critical_trigger_rate": 0.76,
  "trigger_active_rate": 1.0,
  "confidence_mean": 0.9500000000000002,
  "false_intervention_rate": 0.104,
  "repeated_intervention_rate": 0.888,
  "post_intervention_violation_rate": 0.03355704697986577,
  "mean_drift_after_intervention": 8.618206248478435,
  "min_predicted_distance_mean": 3.0983601925960236
}